dima_cli-5.0.9.dist-info/METADATA
dima_cli-5.0.9.dist-info/WHEEL
dima_cli-5.0.9.dist-info/entry_points.txt
dima/exceptions.py
dima/__init__.py
dima/dima_main.py
dima/helpers/__init__.py
dima/bin/__init__.py
dima/bin/_dima.py
dima/dima.cpython-311-x86_64-linux-gnu.so
dima_cli-5.0.9.dist-info/RECORD
