Metadata-Version: 2.3
Name: dima-cli
Version: 5.0.9
Classifier: Programming Language :: Python :: 3.8
Classifier: Programming Language :: Python :: 3.9
Classifier: Programming Language :: Python :: 3.10
Classifier: Programming Language :: Python :: 3.11
Classifier: License :: OSI Approved :: MIT License
Classifier: Operating System :: OS Independent
Classifier: Intended Audience :: Science/Research
Classifier: Natural Language :: English
Summary: A command-line tool that analyses the diversity and motifs of biological sequences
Keywords: bioinformatics,biology,protein,virus,diversity,dna,rna
Author: Shan Tharanga <stwm2@student.london.ac.uk>
Author-email: Shan Tharanga <stwm2@student.london.ac.uk>
License: MIT
Requires-Python: >=3.8, <3.12
Project-URL: Source Code, https://github.com/PU-SDS/DiMA
